{
  "classification": "destroyer",
  "construction": {
    "time": "Cannot Be Constructed"
  },
  "id": "163",
  "name": "Shiratsuyu",
  "nationality": "sakura-empire",
  "slug": "shiratsuyu",
  "stats": {
    "base": {
      "aa": 28,
      "acc": 67,
      "arm": "light",
      "asw": 40,
      "avi": 0,
      "eva": 71,
      "fp": 12,
      "hp": 276,
      "lck": 41,
      "oil": 2,
      "rld": 72
    },
    "lvl100": {
      "aa": 130,
      "acc": 174,
      "arm": "light",
      "asw": 147,
      "avi": 0,
      "eva": 184,
      "fp": 56,
      "hp": 1427,
      "lck": 41,
      "oil": 8,
      "rld": 171
    },
    "lvl100retro": {},
    "lvl120": {
      "aa": 150,
      "acc": 182,
      "arm": "light",
      "asw": 165,
      "avi": 0,
      "eva": 190,
      "fp": 65,
      "hp": 1712,
      "lck": 41,
      "oil": 8,
      "rld": 196
    },
    "lvl120retro": {}
  }
}
